main.py
mseep_mcp2lambda-0.1.3.dist-info/licenses/LICENSE
mseep_mcp2lambda-0.1.3.dist-info/METADATA
mseep_mcp2lambda-0.1.3.dist-info/WHEEL
mseep_mcp2lambda-0.1.3.dist-info/entry_points.txt
mseep_mcp2lambda-0.1.3.dist-info/top_level.txt
mseep_mcp2lambda-0.1.3.dist-info/RECORD
